azure/healthinsights/clinicalmatching/__init__.py
azure/healthinsights/clinicalmatching/_client.py
azure/healthinsights/clinicalmatching/_configuration.py
azure/healthinsights/clinicalmatching/_model_base.py
azure/healthinsights/clinicalmatching/_patch.py
azure/healthinsights/clinicalmatching/_serialization.py
azure/healthinsights/clinicalmatching/_vendor.py
azure/healthinsights/clinicalmatching/_version.py
azure/healthinsights/clinicalmatching/py.typed
azure/healthinsights/clinicalmatching/_operations/__init__.py
azure/healthinsights/clinicalmatching/_operations/_operations.py
azure/healthinsights/clinicalmatching/_operations/_patch.py
azure/healthinsights/clinicalmatching/aio/__init__.py
azure/healthinsights/clinicalmatching/aio/_client.py
azure/healthinsights/clinicalmatching/aio/_configuration.py
azure/healthinsights/clinicalmatching/aio/_patch.py
azure/healthinsights/clinicalmatching/aio/_vendor.py
azure/healthinsights/clinicalmatching/aio/_operations/__init__.py
azure/healthinsights/clinicalmatching/aio/_operations/_operations.py
azure/healthinsights/clinicalmatching/aio/_operations/_patch.py
azure/healthinsights/clinicalmatching/models/__init__.py
azure/healthinsights/clinicalmatching/models/_enums.py
azure/healthinsights/clinicalmatching/models/_models.py
azure/healthinsights/clinicalmatching/models/_patch.py
azure_healthinsights_clinicalmatching-1.0.0b1.post1.dist-info/LICENSE
azure_healthinsights_clinicalmatching-1.0.0b1.post1.dist-info/METADATA
azure_healthinsights_clinicalmatching-1.0.0b1.post1.dist-info/WHEEL
azure_healthinsights_clinicalmatching-1.0.0b1.post1.dist-info/top_level.txt
azure_healthinsights_clinicalmatching-1.0.0b1.post1.dist-info/RECORD
