Metadata-Version: 2.1
Name: azure-healthinsights-clinicalmatching
Version: 1.0.0b1.post1
Summary: Microsoft Cognitive Services Health Insights Clinical Matching Client Library for Python
Home-page: https://github.com/Azure/azure-sdk-for-python/tree/main/sdk
Author: Microsoft Corporation
Author-email: azpysdkhelp@microsoft.com
License: MIT License
Keywords: azure,azure sdk
Classifier: Development Status :: 4 - Beta
Classifier: Programming Language :: Python
Classifier: Programming Language :: Python :: 3 :: Only
Classifier: Programming Language :: Python :: 3
Classifier: Programming Language :: Python :: 3.7
Classifier: Programming Language :: Python :: 3.8
Classifier: Programming Language :: Python :: 3.9
Classifier: Programming Language :: Python :: 3.10
Classifier: Programming Language :: Python :: 3.11
Classifier: License :: OSI Approved :: MIT License
Requires-Python: >=3.7
License-File: LICENSE
Requires-Dist: isodate (<1.0.0,>=0.6.1)
Requires-Dist: azure-core (<2.0.0,>=1.24.0)
Requires-Dist: typing-extensions (>=4.3.0) ; python_version < "3.8.0"
